topsis_mehak/topsis.py
topsis_mehakpreet_102317094-0.1.dist-info/METADATA
topsis_mehakpreet_102317094-0.1.dist-info/WHEEL
topsis_mehakpreet_102317094-0.1.dist-info/entry_points.txt
topsis_mehakpreet_102317094-0.1.dist-info/top_level.txt
topsis_mehakpreet_102317094-0.1.dist-info/RECORD
