Metadata-Version: 2.4
Name: Topsis-Mehakpreet-102317094
Version: 0.1
Requires-Dist: pandas
Requires-Dist: numpy
Dynamic: requires-dist
